{
"type": "FeatureCollection",
"name": "recintos_alcalde_combaya",
"crs": { "type": "name", "properties": { "name": "urn:ogc:def:crs:OGC:1.3:CRS84" } },
"features": [
{ "type": "Feature", "properties": { "asiento": 298.0, "recinto": 2474.0, "NombreRecinto": "Unidad Educativa Eduardo Avaroa", "PATRIA-SOL": 181.0, "PDC": 32.0, "M.P.S.": 8.0, "UPC": 17.0, "votos_totales": 238.0, "VotoBlanco": 5.0, "VotoNulo": 15.0, "InscritosHabilitados": 286.0, "participacion": 83.2, "pct_PATRIA-SOL": 76.1, "pct_PDC": 13.4, "pct_M.P.S.": 3.4, "pct_UPC": 7.1, "ganador": "PATRIA-SOL", "votos_ganador": 181.0, "pct_ganador": 76.1, "partido_2do": "PDC", "votos_2do": 32.0, "pct_2do": 13.4, "margen_victoria": 62.7 }, "geometry": { "type": "Point", "coordinates": [ -68.7542, -15.80447 ] } },
{ "type": "Feature", "properties": { "asiento": 299.0, "recinto": 2492.0, "NombreRecinto": "Esc. Nucleo Ticamblaya", "PATRIA-SOL": 164.0, "PDC": 31.0, "M.P.S.": 4.0, "UPC": 44.0, "votos_totales": 243.0, "VotoBlanco": 1.0, "VotoNulo": 12.0, "InscritosHabilitados": 266.0, "participacion": 91.4, "pct_PATRIA-SOL": 67.5, "pct_PDC": 12.8, "pct_M.P.S.": 1.6, "pct_UPC": 18.1, "ganador": "PATRIA-SOL", "votos_ganador": 164.0, "pct_ganador": 67.5, "partido_2do": "UPC", "votos_2do": 44.0, "pct_2do": 18.1, "margen_victoria": 49.4 }, "geometry": { "type": "Point", "coordinates": [ -68.73175, -15.83537 ] } },
{ "type": "Feature", "properties": { "asiento": 300.0, "recinto": 2472.0, "NombreRecinto": "Esc. Central Sorejaya", "PATRIA-SOL": 46.0, "PDC": 41.0, "M.P.S.": 26.0, "UPC": 311.0, "votos_totales": 424.0, "VotoBlanco": 2.0, "VotoNulo": 95.0, "InscritosHabilitados": 521.0, "participacion": 81.4, "pct_PATRIA-SOL": 10.8, "pct_PDC": 9.7, "pct_M.P.S.": 6.1, "pct_UPC": 73.3, "ganador": "UPC", "votos_ganador": 311.0, "pct_ganador": 73.3, "partido_2do": "PATRIA-SOL", "votos_2do": 46.0, "pct_2do": 10.8, "margen_victoria": 62.5 }, "geometry": { "type": "Point", "coordinates": [ -68.76491, -15.8242 ] } },
{ "type": "Feature", "properties": { "asiento": 3452.0, "recinto": 1.0, "NombreRecinto": "Unidad Educativa Huaycho", "PATRIA-SOL": 109.0, "PDC": 69.0, "M.P.S.": 6.0, "UPC": 1.0, "votos_totales": 185.0, "VotoBlanco": 27.0, "VotoNulo": 28.0, "InscritosHabilitados": 258.0, "participacion": 71.7, "pct_PATRIA-SOL": 58.9, "pct_PDC": 37.3, "pct_M.P.S.": 3.2, "pct_UPC": 0.5, "ganador": "PATRIA-SOL", "votos_ganador": 109.0, "pct_ganador": 58.9, "partido_2do": "PDC", "votos_2do": 69.0, "pct_2do": 37.3, "margen_victoria": 21.6 }, "geometry": { "type": "Point", "coordinates": [ -68.73401, -15.81383 ] } }
]
}
