{
"type": "FeatureCollection",
"name": "recintos_alcalde_santuario_de_quillacas",
"crs": { "type": "name", "properties": { "name": "urn:ogc:def:crs:OGC:1.3:CRS84" } },
"features": [
{ "type": "Feature", "properties": { "asiento": 2091.0, "recinto": 2.0, "NombreRecinto": "U.E. Santuario de Quillacas", "SOMOS": 65.0, "JACHAJAKISASOLFESORC": 805.0, "votos_totales": 870.0, "VotoBlanco": 30.0, "VotoNulo": 27.0, "InscritosHabilitados": 1004.0, "participacion": 86.7, "pct_SOMOS": 7.5, "pct_JACHAJAKISASOLFESORC": 92.5, "ganador": "JACHAJAKISASOLFESORC", "votos_ganador": 805.0, "pct_ganador": 92.5, "partido_2do": "SOMOS", "votos_2do": 65.0, "pct_2do": 7.5, "margen_victoria": 85.0 }, "geometry": { "type": "Point", "coordinates": [ -66.940355, -19.231988 ] } },
{ "type": "Feature", "properties": { "asiento": 2092.0, "recinto": 2.0, "NombreRecinto": "Col. Nal. Mixto Sevaruyo", "SOMOS": 414.0, "JACHAJAKISASOLFESORC": 238.0, "votos_totales": 652.0, "VotoBlanco": 49.0, "VotoNulo": 88.0, "InscritosHabilitados": 869.0, "participacion": 75.0, "pct_SOMOS": 63.5, "pct_JACHAJAKISASOLFESORC": 36.5, "ganador": "SOMOS", "votos_ganador": 414.0, "pct_ganador": 63.5, "partido_2do": "JACHAJAKISASOLFESORC", "votos_2do": 238.0, "pct_2do": 36.5, "margen_victoria": 27.0 }, "geometry": { "type": "Point", "coordinates": [ -66.8639, -19.36308 ] } },
{ "type": "Feature", "properties": { "asiento": 2093.0, "recinto": 2.0, "NombreRecinto": "Esc. Soraga", "SOMOS": 145.0, "JACHAJAKISASOLFESORC": 68.0, "votos_totales": 213.0, "VotoBlanco": 16.0, "VotoNulo": 19.0, "InscritosHabilitados": 280.0, "participacion": 76.1, "pct_SOMOS": 68.1, "pct_JACHAJAKISASOLFESORC": 31.9, "ganador": "SOMOS", "votos_ganador": 145.0, "pct_ganador": 68.1, "partido_2do": "JACHAJAKISASOLFESORC", "votos_2do": 68.0, "pct_2do": 31.9, "margen_victoria": 36.2 }, "geometry": { "type": "Point", "coordinates": [ -66.81366, -19.37804 ] } }
]
}
