{
"type": "FeatureCollection",
"name": "recintos_alcalde_san_rafael",
"crs": { "type": "name", "properties": { "name": "urn:ogc:def:crs:OGC:1.3:CRS84" } },
"features": [
{ "type": "Feature", "properties": { "asiento": 2300.0, "recinto": 24017.0, "NombreRecinto": "U.E. Nacional Godofredo Trenker", "CREEMOS": 385.0, "DEMOCRATAS": 235.0, "UN": 675.0, "TODOS-": 0.0, "PATRIA-UNIDOS": 554.0, "LIBRE": 624.0, "votos_totales": 2473.0, "VotoBlanco": 35.0, "VotoNulo": 83.0, "InscritosHabilitados": 2936.0, "participacion": 84.2, "pct_CREEMOS": 15.6, "pct_DEMOCRATAS": 9.5, "pct_UN": 27.3, "pct_TODOS-": 0.0, "pct_PATRIA-UNIDOS": 22.4, "pct_LIBRE": 25.2, "ganador": "UN", "votos_ganador": 675.0, "pct_ganador": 27.3, "partido_2do": "LIBRE", "votos_2do": 624.0, "pct_2do": 25.2, "margen_victoria": 2.1 }, "geometry": { "type": "Point", "coordinates": [ -60.67352, -16.78576 ] } },
{ "type": "Feature", "properties": { "asiento": 2302.0, "recinto": 6319.0, "NombreRecinto": "U.E. Villa Fatima", "CREEMOS": 14.0, "DEMOCRATAS": 7.0, "UN": 5.0, "TODOS-": 0.0, "PATRIA-UNIDOS": 11.0, "LIBRE": 33.0, "votos_totales": 70.0, "VotoBlanco": 2.0, "VotoNulo": 12.0, "InscritosHabilitados": 100.0, "participacion": 70.0, "pct_CREEMOS": 20.0, "pct_DEMOCRATAS": 10.0, "pct_UN": 7.1, "pct_TODOS-": 0.0, "pct_PATRIA-UNIDOS": 15.7, "pct_LIBRE": 47.1, "ganador": "LIBRE", "votos_ganador": 33.0, "pct_ganador": 47.1, "partido_2do": "CREEMOS", "votos_2do": 14.0, "pct_2do": 20.0, "margen_victoria": 27.1 }, "geometry": { "type": "Point", "coordinates": [ -60.604289, -16.96471 ] } },
{ "type": "Feature", "properties": { "asiento": 2303.0, "recinto": 6320.0, "NombreRecinto": "U.E. El Tuna", "CREEMOS": 21.0, "DEMOCRATAS": 5.0, "UN": 62.0, "TODOS-": 0.0, "PATRIA-UNIDOS": 5.0, "LIBRE": 121.0, "votos_totales": 214.0, "VotoBlanco": 2.0, "VotoNulo": 21.0, "InscritosHabilitados": 280.0, "participacion": 76.4, "pct_CREEMOS": 9.8, "pct_DEMOCRATAS": 2.3, "pct_UN": 29.0, "pct_TODOS-": 0.0, "pct_PATRIA-UNIDOS": 2.3, "pct_LIBRE": 56.5, "ganador": "LIBRE", "votos_ganador": 121.0, "pct_ganador": 56.5, "partido_2do": "UN", "votos_2do": 62.0, "pct_2do": 29.0, "margen_victoria": 27.5 }, "geometry": { "type": "Point", "coordinates": [ -59.698296, -16.631739 ] } },
{ "type": "Feature", "properties": { "asiento": 3551.0, "recinto": 1.0, "NombreRecinto": "U.E. Miraflores", "CREEMOS": 146.0, "DEMOCRATAS": 72.0, "UN": 51.0, "TODOS-": 0.0, "PATRIA-UNIDOS": 47.0, "LIBRE": 224.0, "votos_totales": 540.0, "VotoBlanco": 12.0, "VotoNulo": 37.0, "InscritosHabilitados": 710.0, "participacion": 76.1, "pct_CREEMOS": 27.0, "pct_DEMOCRATAS": 13.3, "pct_UN": 9.4, "pct_TODOS-": 0.0, "pct_PATRIA-UNIDOS": 8.7, "pct_LIBRE": 41.5, "ganador": "LIBRE", "votos_ganador": 224.0, "pct_ganador": 41.5, "partido_2do": "CREEMOS", "votos_2do": 146.0, "pct_2do": 27.0, "margen_victoria": 14.5 }, "geometry": { "type": "Point", "coordinates": [ -60.580512, -17.121726 ] } }
]
}
