{
"type": "FeatureCollection",
"name": "recintos_alcalde_san_ramon",
"crs": { "type": "name", "properties": { "name": "urn:ogc:def:crs:OGC:1.3:CRS84" } },
"features": [
{ "type": "Feature", "properties": { "asiento": 2616.0, "recinto": 1.0, "NombreRecinto": "U.E. Napoleón Añez Ortiz", "DESPIERTA": 1414.0, "MNR": 898.0, "votos_totales": 2312.0, "VotoBlanco": 33.0, "VotoNulo": 36.0, "InscritosHabilitados": 2784.0, "participacion": 83.0, "pct_DESPIERTA": 61.2, "pct_MNR": 38.8, "ganador": "DESPIERTA", "votos_ganador": 1414.0, "pct_ganador": 61.2, "partido_2do": "MNR", "votos_2do": 898.0, "pct_2do": 38.8, "margen_victoria": 22.4 }, "geometry": { "type": "Point", "coordinates": [ -64.61865, -13.26702 ] } },
{ "type": "Feature", "properties": { "asiento": 2617.0, "recinto": 1.0, "NombreRecinto": "Esc. El Poyori", "DESPIERTA": 30.0, "MNR": 15.0, "votos_totales": 45.0, "VotoBlanco": 0.0, "VotoNulo": 0.0, "InscritosHabilitados": 53.0, "participacion": 84.9, "pct_DESPIERTA": 66.7, "pct_MNR": 33.3, "ganador": "DESPIERTA", "votos_ganador": 30.0, "pct_ganador": 66.7, "partido_2do": "MNR", "votos_2do": 15.0, "pct_2do": 33.3, "margen_victoria": 33.4 }, "geometry": { "type": "Point", "coordinates": [ -64.42094, -13.00931 ] } },
{ "type": "Feature", "properties": { "asiento": 3173.0, "recinto": 1.0, "NombreRecinto": "Esc. El Carmen de Guacayane", "DESPIERTA": 39.0, "MNR": 14.0, "votos_totales": 53.0, "VotoBlanco": 1.0, "VotoNulo": 1.0, "InscritosHabilitados": 69.0, "participacion": 76.8, "pct_DESPIERTA": 73.6, "pct_MNR": 26.4, "ganador": "DESPIERTA", "votos_ganador": 39.0, "pct_ganador": 73.6, "partido_2do": "MNR", "votos_2do": 14.0, "pct_2do": 26.4, "margen_victoria": 47.2 }, "geometry": { "type": "Point", "coordinates": [ -64.37999, -13.12766 ] } }
]
}
